{
  "id": "n8n-ion8n-20260721",
  "title": "n8n-io/n8n",
  "source_url": "https://github.com/n8n-io/n8n",
  "source_platform": "github",
  "summary": "n8n 是一个公平代码的工作流自动化平台，具备原生AI能力，支持可视化构建与自定义代码结合，可自托管或使用云服务，拥有400多个集成。",
  "tags": [
    "工作流自动化",
    "AI集成",
    "可视化编程",
    "开源",
    "低代码"
  ],
  "status": "analyzed",
  "created_at": "2026-07-21T10:14:30Z",
  "updated_at": "2026-07-21T10:14:30Z",
  "analysis": {
    "description": "n8n 是一个开源的工作流自动化平台，采用公平代码许可，提供可视化拖拽式工作流编辑器，同时支持自定义代码节点。它原生集成了AI能力，允许用户构建智能自动化流程。平台支持自托管部署或使用其云服务，拥有超过400个集成，覆盖各种主流应用和服务。",
    "tech_category": "AI编程工具",
    "innovation": "将AI能力原生集成到工作流自动化平台，实现可视化与代码的灵活结合。",
    "difficulty": "中等",
    "use_cases": [
      "自动化数据处理与转换",
      "AI驱动的业务流程编排",
      "跨应用集成与数据同步"
    ],
    "score": 9
  }
}